VarInstaller/__init__.py
VarInstaller/bytes.py
VarInstaller/gui.py
lib/__init__.py
lib/bytes.py
lib/gui.py
VarInstaller-1.dist-info/METADATA
VarInstaller-1.dist-info/WHEEL
VarInstaller-1.dist-info/top_level.txt
VarInstaller-1.dist-info/RECORD
